LICENSE
MANIFEST.in
README.md
setup.cfg
setup.py
mTAGs/__init__.py
mTAGs/mtags.py
mTAGs.egg-info/PKG-INFO
mTAGs.egg-info/SOURCES.txt
mTAGs.egg-info/dependency_links.txt
mTAGs.egg-info/entry_points.txt
mTAGs.egg-info/requires.txt
mTAGs.egg-info/top_level.txt
mTAGs/data/arc_lsu.hmm
mTAGs/data/arc_ssu.hmm
mTAGs/data/bac_lsu.hmm
mTAGs/data/bac_ssu.hmm
mTAGs/data/euk_lsu.hmm
mTAGs/data/euk_ssu.hmm
mTAGs/data/lsu.hmm
mTAGs/data/ssu.hmm