Metadata-Version: 2.1
Name: mTAGs
Version: 1.0.4
Summary: mTAGs - taxonomic profiling using degenerate consensus reference sequences of ribosomal RNA gene.
Home-page: https://github.com/SushiLab/mTAGs
Author: Hans-Joachim Ruscheweyh
Author-email: hansr@ethz.ch
License: GPLv3
Download-URL: https://github.com/SushiLab/mTAGs/archive/refs/tags/1.0.4.tar.gz
Keywords: bioinformatics metagenomics ngs 16S
Platform: UNKNOWN
Classifier: Programming Language :: Python
Classifier: Programming Language :: Python :: 3
Classifier: Development Status :: 5 - Production/Stable
Classifier: Intended Audience :: Science/Research
Classifier: Topic :: Scientific/Engineering :: Bio-Informatics
Classifier: License :: OSI Approved :: GNU General Public License v3 (GPLv3)
Classifier: Operating System :: OS Independent
License-File: LICENSE
